graphtastic/__init__.py
graphtastic/clustering.py
graphtastic/convert.py
graphtastic/fit.py
graphtastic/graphs.py
graphtastic/graphtastic.py
graphtastic/hierarchical.py
graphtastic/stats.py
graphtastic/utility.py
graphtastic-0.12.0.dist-info/LICENSE
graphtastic-0.12.0.dist-info/METADATA
graphtastic-0.12.0.dist-info/WHEEL
graphtastic-0.12.0.dist-info/top_level.txt
graphtastic-0.12.0.dist-info/RECORD
