Metadata-Version: 2.1
Name: graphtastic
Version: 0.12.0
Summary: Graphtastic, a Graph Learning library for Humans
Home-page: https://github.com/richardtjornhammar/graphtastic
Author: Richard Tjörnhammar
Author-email: richard.tjornhammar@gmail.com
License: UNKNOWN
Platform: UNKNOWN
Classifier: Programming Language :: Python :: 3.9
Classifier: Programming Language :: Python :: 3.10
Classifier: License :: OSI Approved :: Apache Software License
Classifier: Operating System :: OS Independent
License-File: LICENSE
